lettuce_rest/__init__.py
lettuce_rest/step_definition.py
lettuce_rest-1.0.1.dist-info/METADATA
lettuce_rest-1.0.1.dist-info/RECORD
lettuce_rest-1.0.1.dist-info/WHEEL
lettuce_rest-1.0.1.dist-info/top_level.txt
